bionumpy/__init__.py
bionumpy/cli.py
bionumpy/computation_graph.py
bionumpy/config.py
bionumpy/encoded_array.py
bionumpy/plotting.py
bionumpy/string_array.py
bionumpy/typing.py
bionumpy/alignments/__init__.py
bionumpy/alignments/cigar.py
bionumpy/alignments/msa.py
bionumpy/arithmetics/__init__.py
bionumpy/arithmetics/bedgraph.py
bionumpy/arithmetics/intervals.py
bionumpy/arithmetics/similarity_measures.py
bionumpy/bnpdataclass/__init__.py
bionumpy/bnpdataclass/bnpdataclass.py
bionumpy/bnpdataclass/bnpdataclassfunction.py
bionumpy/bnpdataclass/lazybnpdataclass.py
bionumpy/bnpdataclass/pandas_adaptor.py
bionumpy/cupy_compatible/__init__.py
bionumpy/cupy_compatible/parser.py
bionumpy/datatypes/__init__.py
bionumpy/datatypes/gtf.py
bionumpy/encodings/__init__.py
bionumpy/encodings/_legacy_encodings.py
bionumpy/encodings/alphabet_encoding.py
bionumpy/encodings/base_encoding.py
bionumpy/encodings/bool_encoding.py
bionumpy/encodings/exceptions.py
bionumpy/encodings/integer_encoding.py
bionumpy/encodings/kmer_encodings.py
bionumpy/encodings/string_encodings.py
bionumpy/encodings/vcf_encoding.py
bionumpy/genomic_data/__init__.py
bionumpy/genomic_data/annotation.py
bionumpy/genomic_data/binned_genome.py
bionumpy/genomic_data/coordinate_mapping.py
bionumpy/genomic_data/genome.py
bionumpy/genomic_data/genome_context.py
bionumpy/genomic_data/genome_context_base.py
bionumpy/genomic_data/genomic_data.py
bionumpy/genomic_data/genomic_intervals.py
bionumpy/genomic_data/genomic_sequence.py
bionumpy/genomic_data/genomic_track.py
bionumpy/genomic_data/geometry.py
bionumpy/genomic_data/global_offset.py
bionumpy/io/__init__.py
bionumpy/io/_legacy.py
bionumpy/io/bam.py
bionumpy/io/delimited_buffers.py
bionumpy/io/dump_csv.py
bionumpy/io/exceptions.py
bionumpy/io/fastq_buffer.py
bionumpy/io/file_buffers.py
bionumpy/io/files.py
bionumpy/io/genotype_buffer_extractor.py
bionumpy/io/gfa.py
bionumpy/io/gzip_reading.py
bionumpy/io/headers.py
bionumpy/io/indexed_bam.py
bionumpy-1.0.14.dist-info/LICENSE
bionumpy-1.0.14.dist-info/METADATA
bionumpy-1.0.14.dist-info/WHEEL
bionumpy-1.0.14.dist-info/entry_points.txt
bionumpy-1.0.14.dist-info/top_level.txt
bionumpy-1.0.14.dist-info/RECORD
