Metadata-Version: 2.1
Name: bionumpy
Version: 1.0.14
Summary: Library for working with biological sequence data as numpy arrays.
Home-page: https://github.com/bionumpy/bionumpy
Author: Knut Rand
Author-email: knutdrand@gmail.com
License: MIT license
Keywords: bionumpy
Classifier: Development Status :: 2 - Pre-Alpha
Classifier: Intended Audience :: Developers
Classifier: License :: OSI Approved :: MIT License
Classifier: Natural Language :: English
Classifier: Programming Language :: Python :: 3
Classifier: Programming Language :: Python :: 3.6
Classifier: Programming Language :: Python :: 3.7
Classifier: Programming Language :: Python :: 3.8
Requires-Python: >=3.6
License-File: LICENSE
Requires-Dist: numpy >=1.20
Requires-Dist: npstructures >=0.2.15
Provides-Extra: full
Requires-Dist: isal ; extra == 'full'
